neuromation/__init__.py
neuromation/py.typed
neuromation/api/__init__.py
neuromation/api/abc.py
neuromation/api/admin.py
neuromation/api/blob_storage.py
neuromation/api/client.py
neuromation/api/config.py
neuromation/api/config_factory.py
neuromation/api/core.py
neuromation/api/disks.py
neuromation/api/errors.py
neuromation/api/file_filter.py
neuromation/api/images.py
neuromation/api/jobs.py
neuromation/api/login.py
neuromation/api/parser.py
neuromation/api/parsing_utils.py
neuromation/api/plugins.py
neuromation/api/quota.py
neuromation/api/secrets.py
neuromation/api/server_cfg.py
neuromation/api/storage.py
neuromation/api/tracing.py
neuromation/api/url_utils.py
neuromation/api/users.py
neuromation/api/utils.py
neuromation/cli/__init__.py
neuromation/cli/__main__.py
neuromation/cli/admin.py
neuromation/cli/ael.py
neuromation/cli/alias.py
neuromation/cli/asyncio_utils.py
neuromation/cli/blob_storage.py
neuromation/cli/click_types.py
neuromation/cli/completion.py
neuromation/cli/config.py
neuromation/cli/const.py
neuromation/cli/defaults.py
neuromation/cli/disks.py
neuromation/cli/docker_credential_helper.py
neuromation/cli/image.py
neuromation/cli/job.py
neuromation/cli/log_formatter.py
neuromation/cli/main.py
neuromation/cli/parse_utils.py
neuromation/cli/printer.py
neuromation/cli/project.py
neuromation/cli/root.py
neuromation/cli/secrets.py
neuromation/cli/share.py
neuromation/cli/stats.py
neuromation/cli/storage.py
neuromation/cli/text_helper.py
neuromation/cli/topics.py
neuromation/cli/tty_utils.py
neuromation/cli/utils.py
neuromation/cli/version_utils.py
neuromation/cli/formatters/__init__.py
neuromation/cli/formatters/admin.py
neuromation/cli/formatters/blob_storage.py
neuromation/cli/formatters/config.py
neuromation/cli/formatters/disks.py
neuromation/cli/formatters/ftable.py
neuromation/cli/formatters/images.py
neuromation/cli/formatters/jobs.py
neuromation/cli/formatters/storage.py
neuromation/cli/formatters/utils.py
neuromation-20.12.7.dist-info/LICENSE
neuromation-20.12.7.dist-info/METADATA
neuromation-20.12.7.dist-info/WHEEL
neuromation-20.12.7.dist-info/entry_points.txt
neuromation-20.12.7.dist-info/top_level.txt
neuromation-20.12.7.dist-info/RECORD
